ziafont/__init__.py
ziafont/cmap.py
ziafont/config.py
ziafont/findfont.py
ziafont/font.py
ziafont/fontread.py
ziafont/fonttypes.py
ziafont/glyph.py
ziafont/glyphcff.py
ziafont/glyphglyf.py
ziafont/gpos.py
ziafont/gsub.py
ziafont/inspect.py
ziafont/py.typed
ziafont/svgpath.py
ziafont/tables.py
ziafont/fonts/DejaVuSans.ttf
ziafont/fonts/__init__.py
ziafont-0.10.dist-info/LICENSE.txt
ziafont-0.10.dist-info/METADATA
ziafont-0.10.dist-info/WHEEL
ziafont-0.10.dist-info/top_level.txt
ziafont-0.10.dist-info/RECORD
