Metadata-Version: 2.2
Name: ziafont
Version: 0.10
Summary: Convert TTF/OTF font glyphs to SVG paths
Home-page: https://ziafont.readthedocs.io
Author: Collin J. Delker
Author-email: code@collindelker.com
License: MIT
Project-URL: Documentation, https://ziafont.readthedocs.io
Project-URL: Source Code, https://github.com/cdelker/ziafont
Keywords: font,truetype,opentype,svg,glyph
Classifier: Development Status :: 4 - Beta
Classifier: Programming Language :: Python :: 3
Classifier: Programming Language :: Python :: 3.9
Classifier: Programming Language :: Python :: 3.10
Classifier: Programming Language :: Python :: 3.11
Classifier: Programming Language :: Python :: 3.12
Classifier: Programming Language :: Python :: 3.13
Classifier: License :: OSI Approved :: MIT License
Classifier: Operating System :: OS Independent
Classifier: Intended Audience :: Education
Classifier: Intended Audience :: Science/Research
Classifier: Intended Audience :: End Users/Desktop
Classifier: Intended Audience :: Developers
Requires-Python: >=3.9
License-File: LICENSE.txt
